koyeb/__init__.py
koyeb/api_client.py
koyeb/api_response.py
koyeb/configuration.py
koyeb/exceptions.py
koyeb/rest.py
koyeb_sdk-2025.7.0.dist-info/licenses/LICENSE
koyeb_sdk-2025.7.0.dist-info/METADATA
koyeb_sdk-2025.7.0.dist-info/WHEEL
koyeb_sdk-2025.7.0.dist-info/top_level.txt
koyeb_sdk-2025.7.0.dist-info/RECORD
