Metadata-Version: 2.4
Name: koyeb-sdk
Version: 2025.7.0
Summary: Koyeb Rest API
Author-email: OpenAPI Generator Community <team@openapitools.org>
License-Expression: Apache-2.0
Project-URL: Repository, https://github.com/koyeb/koyeb-api-client-python
Keywords: OpenAPI,OpenAPI-Generator,Koyeb Rest API
Requires-Python: >=3.9
License-File: LICENSE
Requires-Dist: urllib3<3.0.0,>=2.1.0
Requires-Dist: python-dateutil>=2.8.2
Requires-Dist: pydantic>=2
Requires-Dist: typing-extensions>=4.7.1
Dynamic: license-file
